[
  {
    "inventory_id": "Office",
    "item_number": "LINIQ8WZ4314480",
    "item_name": "Vizio V-Series 50\"",
    "description": "4K UHD HDR LED Smart TV",
    "quantity": "1.0",
    "price": "269.99",
    "location": "Common Area",
    "issued_to": "",
    "issued_date": "",
    "notes": ""
  },
  {
    "inventory_id": "Office2",
    "item_number": "LINIQ8WZ4313635",
    "item_name": "Vizio V-Series 50\"",
    "description": "4K UHD HDR LED Smart TV",
    "quantity": "1.0",
    "price": "269.99",
    "location": "Office Room 3",
    "issued_to": "",
    "issued_date": "",
    "notes": ""
  },
  {
    "inventory_id": "Office Printer",
    "item_number": "CVBRR2N4DM",
    "item_name": "HP ColorJet Pro MFP4301",
    "description": "Color Printer",
    "quantity": "1.0",
    "price": "699.99",
    "location": "Common Area",
    "issued_to": "",
    "issued_date": "",
    "notes": ""
  },
  {
    "inventory_id": "WTS Monitor 1",
    "item_number": "3CM3240BXC",
    "item_name": "HP M22f FHD Monitor",
    "description": "Desktop Monitors",
    "quantity": "1.0",
    "price": "144.99",
    "location": "WorkSpace04",
    "issued_to": "Steve Dutter",
    "issued_date": "",
    "notes": ""
  },
  {
    "inventory_id": "WTS Monitor 2",
    "item_number": "3CM328198F",
    "item_name": "HP M22f FHD Monitor",
    "description": "Desktop Monitors",
    "quantity": "1.0",
    "price": "144.99",
    "location": "WorkSpace04",
    "issued_to": "Steve Dutter",
    "issued_date": "",
    "notes": ""
  },
  {
    "inventory_id": "WTS Monitor 3",
    "item_number": "3CM3460JSG",
    "item_name": "HP M22f FHD Monitor",
    "description": "Desktop Monitors",
    "quantity": "1.0",
    "price": "144.99",
    "location": "Cyber Room",
    "issued_to": "",
    "issued_date": "",
    "notes": ""
  },
  {
    "inventory_id": "WTS Monitor 4",
    "item_number": "3CM3460JS6",
    "item_name": "HP M22f FHD Monitor",
    "description": "Desktop Monitors",
    "quantity": "1.0",
    "price": "144.99",
    "location": "Cyber Room",
    "issued_to": "",
    "issued_date": "",
    "notes": ""
  },
  {
    "inventory_id": "WTS Monitor 5",
    "item_number": "3CM3460JSH",
    "item_name": "HP M22f FHD Monitor",
    "description": "Desktop Monitors",
    "quantity": "1.0",
    "price": "144.99",
    "location": "WorkSpace04",
    "issued_to": "Ken Stein",
    "issued_date": "",
    "notes": ""
  },
  {
    "inventory_id": "WTS Monitor 6",
    "item_number": "3CM3460JTD",
    "item_name": "HP M22f FHD Monitor",
    "description": "Desktop Monitors",
    "quantity": "1.0",
    "price": "144.99",
    "location": "Office Room 1",
    "issued_to": "Ken Stein",
    "issued_date": "",
    "notes": ""
  },
  {
    "inventory_id": "WTS Monitor 7",
    "item_number": "3CM3460JS4",
    "item_name": "HP M22f FHD Monitor",
    "description": "Desktop Monitors",
    "quantity": "1.0",
    "price": "144.99",
    "location": "Office Room 3",
    "issued_to": "Jan Miketa",
    "issued_date": "",
    "notes": ""
  },
  {
    "inventory_id": "WTS Monitor 8",
    "item_number": "3CM3460JSD",
    "item_name": "HP M22f FHD Monitor",
    "description": "Desktop Monitors",
    "quantity": "1.0",
    "price": "144.99",
    "location": "Office Room 3",
    "issued_to": "Jan Miketa",
    "issued_date": "",
    "notes": ""
  },
  {
    "inventory_id": "WTS Monitor 9",
    "item_number": "3CM3460JS7",
    "item_name": "HP M22f FHD Monitor",
    "description": "Desktop Monitors",
    "quantity": "1.0",
    "price": "144.99",
    "location": "Office Room 3",
    "issued_to": "Becky Sowell",
    "issued_date": "",
    "notes": ""
  },
  {
    "inventory_id": "WTS Monitor 10",
    "item_number": "3CM3460JSJ",
    "item_name": "HP M22f FHD Monitor",
    "description": "Desktop Monitors",
    "quantity": "1.0",
    "price": "144.99",
    "location": "Office Room 3",
    "issued_to": "Becky Sowell",
    "issued_date": "",
    "notes": ""
  },
  {
    "inventory_id": "WTS Monitor 11",
    "item_number": "3CM4200JJY",
    "item_name": "HP M22f FHD Monitor",
    "description": "Desktop Monitors",
    "quantity": "1.0",
    "price": "144.99",
    "location": "Office Room 3",
    "issued_to": "Carole Zehner",
    "issued_date": "",
    "notes": ""
  },
  {
    "inventory_id": "WTS Monitor 12",
    "item_number": "3CM4150HYY",
    "item_name": "HP M22f FHD Monitor",
    "description": "Desktop Monitors",
    "quantity": "1.0",
    "price": "144.99",
    "location": "Office Room 3",
    "issued_to": "Carole Zehner",
    "issued_date": "",
    "notes": ""
  },
  {
    "inventory_id": "WTS Monitor 13",
    "item_number": "3CM4236RRG",
    "item_name": "HP M22f FHD Monitor",
    "description": "Desktop Monitors",
    "quantity": "1.0",
    "price": "144.99",
    "location": "Office Room 2",
    "issued_to": "Jackie Chrabot",
    "issued_date": "",
    "notes": ""
  },
  {
    "inventory_id": "WTS Monitor 14",
    "item_number": "3CM4230RRW",
    "item_name": "HP M22f FHD Monitor",
    "description": "Desktop Monitors",
    "quantity": "1.0",
    "price": "144.99",
    "location": "Office Room 2",
    "issued_to": "Jackie Chrabot",
    "issued_date": "",
    "notes": ""
  },
  {
    "inventory_id": "WTS Monitor 15",
    "item_number": "3CM42913TX",
    "item_name": "HP M22f FHD Monitor",
    "description": "Desktop Monitors",
    "quantity": "1.0",
    "price": "144.99",
    "location": "Cyber Room",
    "issued_to": "",
    "issued_date": "",
    "notes": ""
  },
  {
    "inventory_id": "WTS Monitor 16",
    "item_number": "3CM42914HZ",
    "item_name": "HP M22f FHD Monitor",
    "description": "Desktop Monitors",
    "quantity": "1.0",
    "price": "144.99",
    "location": "Cyber Room",
    "issued_to": "",
    "issued_date": "",
    "notes": ""
  },
  {
    "inventory_id": "WTS LT-0001",
    "item_number": "HS6H1Z3",
    "item_name": "DELL VOSTRO 15 LAPTOP",
    "description": "Laptop",
    "quantity": "1.0",
    "price": "849.0",
    "location": "Jacob Gonzales",
    "issued_to": "Jacob Gonzales",
    "issued_date": "Nov. 2025",
    "notes": ""
  },
  {
    "inventory_id": "WTS LT-0002",
    "item_number": "6TM61Z3",
    "item_name": "DELL VOSTRO 15 LAPTOP 3530",
    "description": "Laptop",
    "quantity": "1.0",
    "price": "849.0",
    "location": "Office Room 3",
    "issued_to": "Carole Zehner",
    "issued_date": "Sep. 2025",
    "notes": ""
  },
  {
    "inventory_id": "WTS LT-0003",
    "item_number": "3ZKH1Z3",
    "item_name": "DELL VOSTRO 15 LAPTOP 3530",
    "description": "Laptop",
    "quantity": "1.0",
    "price": "849.0",
    "location": "Office Room 3",
    "issued_to": "Becky Sowell",
    "issued_date": "Sep. 2024",
    "notes": ""
  },
  {
    "inventory_id": "WTS LT-0004",
    "item_number": "G9RH1Z3",
    "item_name": "DELL VOSTRO 15 LAPTOP 3530",
    "description": "Laptop",
    "quantity": "1.0",
    "price": "849.0",
    "location": "Office Room 1",
    "issued_to": "Ken Stein",
    "issued_date": "Jan. 2024",
    "notes": ""
  },
  {
    "inventory_id": "WTS LT-0005",
    "item_number": "5CG93373QP",
    "item_name": "HP ELITEBOOK 840 G5",
    "description": "Laptop",
    "quantity": "1.0",
    "price": "674.99",
    "location": "Assigned to Jacqueline",
    "issued_to": "Jackie Chrabot",
    "issued_date": "Mar. 2025",
    "notes": ""
  },
  {
    "inventory_id": "WTS LT-0006",
    "item_number": "TA850612",
    "item_name": "HP ELITEBOOK 840 G5",
    "description": "Laptop",
    "quantity": "1.0",
    "price": "674.99",
    "location": "(RETIRED/BROKEN)",
    "issued_to": "",
    "issued_date": "",
    "notes": ""
  },
  {
    "inventory_id": "WTS LT-0007",
    "item_number": "5CG9112HB5",
    "item_name": "HP ELITEBOOK 840 G6",
    "description": "Laptop",
    "quantity": "1.0",
    "price": "674.99",
    "location": "Cyber Room",
    "issued_to": "",
    "issued_date": "",
    "notes": ""
  },
  {
    "inventory_id": "WTS LT-0008",
    "item_number": "A131ZJUA#ABA",
    "item_name": "HP OMNIBOOK 14",
    "description": "Laptop",
    "quantity": "1.0",
    "price": "1499.99",
    "location": "Assigned to Tom",
    "issued_to": "Tom Crain",
    "issued_date": "Jun. 2024",
    "notes": ""
  },
  {
    "inventory_id": "WTS LT-0009",
    "item_number": "ST: F7RH1Z3",
    "item_name": "DELL VOSTRO 15 LAPTOP 3530",
    "description": "Laptop",
    "quantity": "1.0",
    "price": "849.0",
    "location": "Office Room 3",
    "issued_to": "Jan Miketa",
    "issued_date": "",
    "notes": ""
  },
  {
    "inventory_id": "OfficeDesk1",
    "item_number": "8QSTAD",
    "item_name": "HON Executive Desk  H10712L.JJ",
    "description": "Office desk (L-shape) Bowfront",
    "quantity": "1.0",
    "price": "499.99",
    "location": "WorkSpace04",
    "issued_to": "Steve Dutter",
    "issued_date": "",
    "notes": ""
  },
  {
    "inventory_id": "OfficeDesk2",
    "item_number": "C7U52A( LEFTSIDE) CUU5EA (RIGHTSIDE)",
    "item_name": "HON Executive Desk 101064 JJ",
    "description": "Office desk (L-shape)",
    "quantity": "1.0",
    "price": "499.99",
    "location": "Unassigned",
    "issued_to": "",
    "issued_date": "",
    "notes": ""
  },
  {
    "inventory_id": "OfficeDesk3",
    "item_number": "86STAD",
    "item_name": "HON Executive Desk H10712L.JJ",
    "description": "Office desk (L-shape)",
    "quantity": "1.0",
    "price": "499.99",
    "location": "Unassigned",
    "issued_to": "",
    "issued_date": "",
    "notes": ""
  },
  {
    "inventory_id": "OfficeDesk4",
    "item_number": "CKU52A (LEFTSIDE) CRU5EA (RIGHTSIDE)",
    "item_name": "HON Executive Desk 101064 JJ",
    "description": "Office desk (L-shape)",
    "quantity": "1.0",
    "price": "499.99",
    "location": "Office Room 2",
    "issued_to": "Jackie Chrabot",
    "issued_date": "",
    "notes": ""
  },
  {
    "inventory_id": "Micro01",
    "item_number": "T230730040990",
    "item_name": "Cuisinart Microwave Oven",
    "description": "Office Microwave",
    "quantity": "1.0",
    "price": "109.99",
    "location": "Breakroom Kitchen",
    "issued_to": "",
    "issued_date": "",
    "notes": ""
  },
  {
    "inventory_id": "WTS1 Phone",
    "item_number": "FVH27040",
    "item_name": "Cisco IP Phone 8851",
    "description": "Desk Phone",
    "quantity": "1.0",
    "price": "350.0",
    "location": "Office Room 4",
    "issued_to": "Steve Dutter",
    "issued_date": "",
    "notes": ""
  },
  {
    "inventory_id": "WTS2 Phone",
    "item_number": "FVH27040J2P",
    "item_name": "Cisco IP Phone 8851",
    "description": "Desk Phone",
    "quantity": "1.0",
    "price": "350.0",
    "location": "Cyber Room",
    "issued_to": "",
    "issued_date": "",
    "notes": ""
  },
  {
    "inventory_id": "WTS3 Phone",
    "item_number": "FVH27040FPQ",
    "item_name": "Cisco IP Phone 8851",
    "description": "Desk Phone",
    "quantity": "1.0",
    "price": "350.0",
    "location": "Office Room 1",
    "issued_to": "Ken Stein",
    "issued_date": "",
    "notes": ""
  },
  {
    "inventory_id": "WTS4 Phone",
    "item_number": "FVH27040K0H",
    "item_name": "Cisco IP Phone 8851",
    "description": "Desk Phone",
    "quantity": "1.0",
    "price": "350.0",
    "location": "Unassigned",
    "issued_to": "Retrieving data. Wait a few seconds and try to cut or copy again.",
    "issued_date": "",
    "notes": ""
  },
  {
    "inventory_id": "WTS5 Phone",
    "item_number": "FVH27040N3H",
    "item_name": "Cisco IP Phone 8851",
    "description": "Desk Phone",
    "quantity": "1.0",
    "price": "350.0",
    "location": "Unassigned",
    "issued_to": "Retrieving data. Wait a few seconds and try to cut or copy again.",
    "issued_date": "",
    "notes": ""
  },
  {
    "inventory_id": "BLKFC01",
    "item_number": "",
    "item_name": "Haworth Zody Multifunction Task Chair Black",
    "description": "BLACK Office Chair",
    "quantity": "1.0",
    "price": "229.99",
    "location": "WorkSpace04",
    "issued_to": "Steve Dutter",
    "issued_date": "",
    "notes": ""
  },
  {
    "inventory_id": "BLKFC02",
    "item_number": "",
    "item_name": "Haworth Zody Multifunction Task Chair Black",
    "description": "BLACK Office Chair",
    "quantity": "1.0",
    "price": "229.99",
    "location": "Office Room 1",
    "issued_to": "Ken Stein",
    "issued_date": "",
    "notes": ""
  },
  {
    "inventory_id": "BLKFC03",
    "item_number": "",
    "item_name": "Haworth Zody Multifunction Task Chair Black",
    "description": "BLACK Office Chair",
    "quantity": "1.0",
    "price": "229.99",
    "location": "Office space (UNASSIGNED)",
    "issued_to": "",
    "issued_date": "",
    "notes": ""
  },
  {
    "inventory_id": "BLKFC04",
    "item_number": "",
    "item_name": "Haworth Zody Multifunction Task Chair Black",
    "description": "BLACK Office Chair",
    "quantity": "1.0",
    "price": "229.99",
    "location": "Office space (UNASSIGNED)",
    "issued_to": "",
    "issued_date": "",
    "notes": ""
  },
  {
    "inventory_id": "BLKFC05",
    "item_number": "",
    "item_name": "Haworth Zody Multifunction Task Chair Black",
    "description": "BLACK Office Chair",
    "quantity": "1.0",
    "price": "229.99",
    "location": "Office space",
    "issued_to": "",
    "issued_date": "",
    "notes": ""
  },
  {
    "inventory_id": "BLUFC01",
    "item_number": "",
    "item_name": "Global Granada Multi-Function Task Chair",
    "description": "BLUE Office chair",
    "quantity": "1.0",
    "price": "129.99",
    "location": "Office space",
    "issued_to": "",
    "issued_date": "",
    "notes": ""
  },
  {
    "inventory_id": "BLUFC02",
    "item_number": "",
    "item_name": "Global Granada Multi-Function Task Chair",
    "description": "BLUE Office chair",
    "quantity": "1.0",
    "price": "129.99",
    "location": "Office space",
    "issued_to": "",
    "issued_date": "",
    "notes": ""
  },
  {
    "inventory_id": "BLUFC03",
    "item_number": "",
    "item_name": "Global Granada Multi-Function Task Chair",
    "description": "BLUE Office chair",
    "quantity": "1.0",
    "price": "129.99",
    "location": "Office space",
    "issued_to": "",
    "issued_date": "",
    "notes": ""
  },
  {
    "inventory_id": "BLUFC04",
    "item_number": "",
    "item_name": "Global Granada Multi-Function Task Chair",
    "description": "BLUE Office chair",
    "quantity": "1.0",
    "price": "129.99",
    "location": "Office space",
    "issued_to": "",
    "issued_date": "",
    "notes": ""
  },
  {
    "inventory_id": "BLUFC05",
    "item_number": "",
    "item_name": "Global Granada Multi-Function Task Chair",
    "description": "BLUE Office chair",
    "quantity": "1.0",
    "price": "129.99",
    "location": "Office space",
    "issued_to": "",
    "issued_date": "",
    "notes": ""
  },
  {
    "inventory_id": "BLUFC06",
    "item_number": "",
    "item_name": "Global Granada Multi-Function Task Chair",
    "description": "BLUE Office chair",
    "quantity": "1.0",
    "price": "129.99",
    "location": "Office space",
    "issued_to": "",
    "issued_date": "",
    "notes": ""
  },
  {
    "inventory_id": "BLUFC07",
    "item_number": "",
    "item_name": "Global Granada Multi-Function Task Chair",
    "description": "BLUE Office chair",
    "quantity": "1.0",
    "price": "129.99",
    "location": "Office space",
    "issued_to": "",
    "issued_date": "",
    "notes": ""
  },
  {
    "inventory_id": "BLUFC08",
    "item_number": "",
    "item_name": "Global Granada Multi-Function Task Chair",
    "description": "BLUE Office chair",
    "quantity": "1.0",
    "price": "129.99",
    "location": "Office space",
    "issued_to": "",
    "issued_date": "",
    "notes": ""
  },
  {
    "inventory_id": "BAC01",
    "item_number": "",
    "item_name": "Sit On It Guest Arm Chair Blue",
    "description": "Arm Chair",
    "quantity": "1.0",
    "price": "79.99",
    "location": "WorkSpace04",
    "issued_to": "Steve Dutter",
    "issued_date": "",
    "notes": ""
  },
  {
    "inventory_id": "BAC02",
    "item_number": "",
    "item_name": "Sit On It Guest Arm Chair Blue",
    "description": "Arm Chair",
    "quantity": "1.0",
    "price": "79.99",
    "location": "WorkSpace04",
    "issued_to": "Steve Dutter",
    "issued_date": "",
    "notes": ""
  },
  {
    "inventory_id": "RT01",
    "item_number": "",
    "item_name": "Office sourse 36\" Round discussion Table",
    "description": "lounge table (round)",
    "quantity": "1.0",
    "price": "149.99",
    "location": "Employee Breakroom",
    "issued_to": "",
    "issued_date": "",
    "notes": ""
  },
  {
    "inventory_id": "Cube 1",
    "item_number": "",
    "item_name": "Cubicle",
    "description": "Workstation",
    "quantity": "1.0",
    "price": "800.0",
    "location": "WorkSpace03",
    "issued_to": "",
    "issued_date": "",
    "notes": ""
  },
  {
    "inventory_id": "Cube 2",
    "item_number": "",
    "item_name": "Cubicle",
    "description": "Workstation",
    "quantity": "1.0",
    "price": "800.0",
    "location": "WorkSpace03",
    "issued_to": "",
    "issued_date": "",
    "notes": ""
  },
  {
    "inventory_id": "Cube 3",
    "item_number": "",
    "item_name": "Cubicle",
    "description": "Workstation",
    "quantity": "1.0",
    "price": "800.0",
    "location": "WorkSpace03",
    "issued_to": "",
    "issued_date": "",
    "notes": ""
  },
  {
    "inventory_id": "Cube 4",
    "item_number": "",
    "item_name": "Cubicle",
    "description": "Workstation",
    "quantity": "1.0",
    "price": "800.0",
    "location": "WorkSpace03",
    "issued_to": "",
    "issued_date": "",
    "notes": ""
  },
  {
    "inventory_id": "Cube 5",
    "item_number": "",
    "item_name": "Cubicle",
    "description": "Workstation",
    "quantity": "1.0",
    "price": "800.0",
    "location": "Common Area",
    "issued_to": "",
    "issued_date": "",
    "notes": ""
  },
  {
    "inventory_id": "Cube 6",
    "item_number": "",
    "item_name": "Cubicle",
    "description": "Workstation",
    "quantity": "1.0",
    "price": "800.0",
    "location": "Common Area",
    "issued_to": "",
    "issued_date": "",
    "notes": ""
  },
  {
    "inventory_id": "Cube 7",
    "item_number": "",
    "item_name": "Cubicle",
    "description": "Workstation",
    "quantity": "1.0",
    "price": "800.0",
    "location": "Common Area",
    "issued_to": "",
    "issued_date": "",
    "notes": ""
  },
  {
    "inventory_id": "Cube 8",
    "item_number": "",
    "item_name": "Cubicle",
    "description": "Workstation",
    "quantity": "1.0",
    "price": "800.0",
    "location": "WorkSpace01",
    "issued_to": "",
    "issued_date": "",
    "notes": ""
  },
  {
    "inventory_id": "Cube 9",
    "item_number": "",
    "item_name": "Cubicle",
    "description": "Workstation",
    "quantity": "1.0",
    "price": "800.0",
    "location": "WorkSpace01",
    "issued_to": "",
    "issued_date": "",
    "notes": ""
  },
  {
    "inventory_id": "REFER01",
    "item_number": "",
    "item_name": "Whirlpool",
    "description": "Refridgerator",
    "quantity": "1.0",
    "price": "159.99",
    "location": "Employee Breakroom",
    "issued_to": "",
    "issued_date": "",
    "notes": ""
  },
  {
    "inventory_id": "SHREDDER01",
    "item_number": "24040100058",
    "item_name": "Kitnery",
    "description": "CUI Shredder",
    "quantity": "1.0",
    "price": "369.0",
    "location": "Common Area",
    "issued_to": "",
    "issued_date": "",
    "notes": "kitnery.us@outlook.com"
  },
  {
    "inventory_id": "Trash Can 1",
    "item_number": "",
    "item_name": "Highmark",
    "description": "Trash Can",
    "quantity": "1.0",
    "price": "14.99",
    "location": "Office Space",
    "issued_to": "",
    "issued_date": "",
    "notes": ""
  },
  {
    "inventory_id": "Trash Can 2",
    "item_number": "",
    "item_name": "Highmark",
    "description": "Trash Can",
    "quantity": "1.0",
    "price": "14.99",
    "location": "Kitchen Breakroom",
    "issued_to": "",
    "issued_date": "",
    "notes": ""
  },
  {
    "inventory_id": "Trash Can 3",
    "item_number": "",
    "item_name": "Highmark",
    "description": "Trash Can",
    "quantity": "1.0",
    "price": "14.99",
    "location": "Office Space",
    "issued_to": "",
    "issued_date": "",
    "notes": ""
  },
  {
    "inventory_id": "Trash Can 4",
    "item_number": "",
    "item_name": "Highmark",
    "description": "Trash Can",
    "quantity": "1.0",
    "price": "14.99",
    "location": "Office Space",
    "issued_to": "",
    "issued_date": "",
    "notes": ""
  },
  {
    "inventory_id": "Trash Can 5",
    "item_number": "",
    "item_name": "Highmark",
    "description": "Trash Can",
    "quantity": "1.0",
    "price": "14.99",
    "location": "Office Space",
    "issued_to": "",
    "issued_date": "",
    "notes": ""
  },
  {
    "inventory_id": "Trash Can 6",
    "item_number": "",
    "item_name": "Highmark",
    "description": "Trash Can",
    "quantity": "1.0",
    "price": "14.99",
    "location": "Office Space",
    "issued_to": "",
    "issued_date": "",
    "notes": ""
  },
  {
    "inventory_id": "Trash Can 7",
    "item_number": "",
    "item_name": "Highmark",
    "description": "Trash Can",
    "quantity": "1.0",
    "price": "14.99",
    "location": "Office Space",
    "issued_to": "",
    "issued_date": "",
    "notes": ""
  },
  {
    "inventory_id": "Teleconference Puck",
    "item_number": "EERXK9",
    "item_name": "Poly Sync",
    "description": "Teleconference Puck",
    "quantity": "1.0",
    "price": "139.99",
    "location": "Assigned to Tom",
    "issued_to": "Tom Crain",
    "issued_date": "",
    "notes": ""
  },
  {
    "inventory_id": "SW001",
    "item_number": "",
    "item_name": "MSI",
    "description": "Dev Laptop",
    "quantity": "",
    "price": "",
    "location": "Office Room 3",
    "issued_to": "Jan Miketa",
    "issued_date": "",
    "notes": ""
  }
]